knotted_graph/NodalSkeleton.py
knotted_graph/__init__.py
knotted_graph/examples.py
knotted_graph/surface_modes.py
knotted_graph/util.py
knotted_graph/vis.py
knotted_graph/yamada/__init__.py
knotted_graph/yamada/geom.py
knotted_graph/yamada/pd_code.py
knotted_graph/yamada/polynomial.py
knotted_graph/yamada/util.py
knotted_graph-0.1.2.dist-info/METADATA
knotted_graph-0.1.2.dist-info/WHEEL
knotted_graph-0.1.2.dist-info/licenses/LICENSE
knotted_graph-0.1.2.dist-info/RECORD
