Metadata-Version: 2.4
Name: knotted_graph
Version: 0.1.2
Dynamic: Summary
Project-URL: Homepage, https://github.com/sarinstein-yan/Nodal-Knot
Project-URL: Repository, https://github.com/sarinstein-yan/Nodal-Knot
Project-URL: PyPI, https://pypi.org/project/knotted_graph/
Author-email: "Xianquan (Sarinstein) Yan" <xianquanyan@gmail.com>, Hakan Akgün <hakanakgun317@gmail.com>
Maintainer-email: "Xianquan (Sarinstein) Yan" <xianquanyan@gmail.com>, Hakan Akgün <hakanakgun317@gmail.com>
License: MIT License
License-File: LICENSE
Keywords: exceptional surface,knotted graph,medial axis,morphological image processing,nodal structure,non-Hermitian topology,skeleton graph,spatial multigraph
Classifier: Development Status :: 2 - Pre-Alpha
Classifier: Intended Audience :: Science/Research
Classifier: License :: OSI Approved :: MIT License
Classifier: Programming Language :: Python :: 3 :: Only
Classifier: Programming Language :: Python :: 3.11
Classifier: Programming Language :: Python :: 3.12
Classifier: Programming Language :: Python :: 3.13
Requires-Python: >=3.11
Requires-Dist: fastrdp
Requires-Dist: jupyterlab
Requires-Dist: minorminer
Requires-Dist: poly2graph
Requires-Dist: pyvista[all]
Requires-Dist: shapely
Requires-Dist: tabulate
Requires-Dist: tqdm
Provides-Extra: all
Requires-Dist: igraph; extra == 'all'
Requires-Dist: plotly; extra == 'all'
